MANIFEST.in
README.txt
setup.cfg
setup.py
demoproj/__init__.py
demoproj/ipythonrc.py
demoproj/manage.py
demoproj/settings.py
demoproj/urls.py
docs/forms.html
docs/index.html
docs/install.html
docs/models.html
docs/overview.html
docs/syntax.html
docs/templates.html
docs/utilities.html
docs/views.html
softwarefabrica/__init__.py
softwarefabrica.django.wiki.egg-info/PKG-INFO
softwarefabrica.django.wiki.egg-info/SOURCES.txt
softwarefabrica.django.wiki.egg-info/dependency_links.txt
softwarefabrica.django.wiki.egg-info/entry_points.txt
softwarefabrica.django.wiki.egg-info/namespace_packages.txt
softwarefabrica.django.wiki.egg-info/not-zip-safe
softwarefabrica.django.wiki.egg-info/requires.txt
softwarefabrica.django.wiki.egg-info/top_level.txt
softwarefabrica/django/__init__.py
softwarefabrica/django/wiki/__init__.py
softwarefabrica/django/wiki/bzrcachedrev.py
softwarefabrica/django/wiki/models.py
softwarefabrica/django/wiki/sanitize.py
softwarefabrica/django/wiki/urls.py
softwarefabrica/django/wiki/version.py
softwarefabrica/django/wiki/views.py
softwarefabrica/django/wiki/wikiparse.py
softwarefabrica/django/wiki/importer/__init__.py
softwarefabrica/django/wiki/importer/twiki.py
softwarefabrica/django/wiki/sync/__init__.py
softwarefabrica/django/wiki/sync/sync.py
softwarefabrica/django/wiki/templatetags/__init__.py
softwarefabrica/django/wiki/templatetags/in_list.py
softwarefabrica/django/wiki/templatetags/pagelink.py
softwarefabrica/django/wiki/templatetags/recentpages.py
softwarefabrica/django/wiki/templatetags/sanitize.py
softwarefabrica/django/wiki/templatetags/wiki.py
softwarefabrica/django/wiki/templatetags/wikilink.py
softwarefabrica/django/wiki/templatetags/wikimenu.py
softwarefabrica/django/wiki/templatetags/wikis.py