Metadata-Version: 1.0
Name: softwarefabrica.django.wiki
Version: 1.0dev-BZR-r41-panta-elasticworld.org-20091021142923-1pr063zdcx4129ba
Summary: A simple but very flexible django wiki application
Home-page: http://pypi.python.org/pypi/softwarefabrica.django.wiki/
Author: Marco Pantaleoni
Author-email: m.pantaleoni@softwarefabrica.org
License: GNU GPL v2
Download-URL: http://pypi.python.org/packages/source/s/softwarefabrica.django.wiki/softwarefabrica.django.wiki-1.0dev-BZR-r41-panta-elasticworld.org-20091021142923-1pr063zdcx4129ba.tar.gz
Keywords: django wiki softwarefabrica
Platform: UNKNOWN
Classifier: Development Status :: 4 - Beta
Classifier: Framework :: Django
Classifier: Intended Audience :: Developers
Classifier: License :: OSI Approved :: GNU General Public License (GPL)
Classifier: Operating System :: OS Independent
Classifier: Programming Language :: Python :: 2.3
Classifier: Topic :: Software Development :: Libraries :: Python Modules
